{
    "bn": "programming_for_iot/aa2021/SmartRecoveryHouse/ecosystem/sensors/3",
    "e": [
        [
            {
                "n": "Patient_Weight",
                "u": "Kg",
                "t": "1621557921.6278431",
                "v": 36.67230455962423
            }
        ],
        [
            {
                "n": "Patient_Weight",
                "u": "Kg",
                "t": "1621557924.6436443",
                "v": 36.692592782807274
            }
        ],
        [
            {
                "n": "Patient_Weight",
                "u": "Kg",
                "t": "1621557927.6518514",
                "v": 36.71285040770198
            }
        ],
        [
            {
                "n": "Patient_Weight",
                "u": "Kg",
                "t": "1621557930.6691036",
                "v": 36.54553588703412
            }
        ],
        [
            {
                "n": "Patient_Weight",
                "u": "Kg",
                "t": "1621557933.6715002",
                "v": 36.784179169261094
            }
        ],
        [
            {
                "n": "Patient_Weight",
                "u": "Kg",
                "t": "1621557936.675694",
                "v": 36.80825107667984
            }
        ],
        [
            {
                "n": "Patient_Weight",
                "u": "Kg",
                "t": "1621557939.6910622",
                "v": 36.773150531079466
            }
        ],
        [
            {
                "n": "Patient_Weight",
                "u": "Kg",
                "t": "1621557942.6965055",
                "v": 36.87361735835795
            }
        ],
        [
            {
                "n": "Patient_Weight",
                "u": "Kg",
                "t": "1621557945.700652",
                "v": 36.78286932528624
            }
        ],
        [
            {
                "n": "Patient_Weight",
                "u": "Kg",
                "t": "1621557948.7134163",
                "v": 36.87788552112569
            }
        ],
        [
            {
                "n": "Patient_Weight",
                "u": "Kg",
                "t": "1621557951.7215657",
                "v": 37.31910601830302
            }
        ],
        [
            {
                "n": "Patient_Weight",
                "u": "Kg",
                "t": "1621557954.729123",
                "v": 36.86716922388275
            }
        ],
        [
            {
                "n": "Patient_Weight",
                "u": "Kg",
                "t": "1621557957.7396333",
                "v": 37.51640898817838
            }
        ],
        [
            {
                "n": "Patient_Weight",
                "u": "Kg",
                "t": "1621557960.7433689",
                "v": 37.5990248976124
            }
        ],
        [
            {
                "n": "Patient_Weight",
                "u": "Kg",
                "t": "1621557963.7580276",
                "v": 36.76504498952962
            }
        ],
        [
            {
                "n": "Patient_Weight",
                "u": "Kg",
                "t": "1621557966.769483",
                "v": 36.877233837124685
            }
        ],
        [
            {
                "n": "Patient_Weight",
                "u": "Kg",
                "t": "1621557969.777663",
                "v": 36.90416276059905
            }
        ],
        [
            {
                "n": "Patient_Weight",
                "u": "Kg",
                "t": "1621557972.7903156",
                "v": 36.7444129698217
            }
        ],
        [
            {
                "n": "Patient_Weight",
                "u": "Kg",
                "t": "1621557975.8204403",
                "v": 36.780060208367324
            }
        ],
        [
            {
                "n": "Patient_Weight",
                "u": "Kg",
                "t": "1621557978.8367877",
                "v": 36.883236439466735
            }
        ],
        [
            {
                "n": "Patient_Weight",
                "u": "Kg",
                "t": "1621557981.8468313",
                "v": 36.79640149364317
            }
        ],
        [
            {
                "n": "Patient_Weight",
                "u": "Kg",
                "t": "1621557984.8604748",
                "v": 36.891189297850595
            }
        ],
        [
            {
                "n": "Patient_Weight",
                "u": "Kg",
                "t": "1621557987.8683586",
                "v": 36.77410522137679
            }
        ],
        [
            {
                "n": "Patient_Weight",
                "u": "Kg",
                "t": "1621557990.8820984",
                "v": 36.80669576296325
            }
        ],
        [
            {
                "n": "Patient_Weight",
                "u": "Kg",
                "t": "1621557993.8892987",
                "v": 61.61162516061965
            }
        ],
        [
            {
                "n": "Patient_Weight",
                "u": "Kg",
                "t": "1621557996.903722",
                "v": 61.69562952900881
            }
        ],
        [
            {
                "n": "Patient_Weight",
                "u": "Kg",
                "t": "1621557999.9171298",
                "v": 61.658216847318855
            }
        ],
        [
            {
                "n": "Patient_Weight",
                "u": "Kg",
                "t": "1621558002.936334",
                "v": 61.61189661767588
            }
        ],
        [
            {
                "n": "Patient_Weight",
                "u": "Kg",
                "t": "1621558005.9536374",
                "v": 61.836811455073885
            }
        ],
        [
            {
                "n": "Patient_Weight",
                "u": "Kg",
                "t": "1621558008.9613242",
                "v": 61.93195088765089
            }
        ],
        [
            {
                "n": "Patient_Weight",
                "u": "Kg",
                "t": "1621558011.968228",
                "v": 61.763707073319026
            }
        ],
        [
            {
                "n": "Patient_Weight",
                "u": "Kg",
                "t": "1621558014.9858172",
                "v": 61.87100596640568
            }
        ],
        [
            {
                "n": "Patient_Weight",
                "u": "Kg",
                "t": "1621558017.998223",
                "v": 61.783922880068936
            }
        ],
        [
            {
                "n": "Patient_Weight",
                "u": "Kg",
                "t": "1621558021.0014775",
                "v": 61.926238437732806
            }
        ],
        [
            {
                "n": "Patient_Weight",
                "u": "Kg",
                "t": "1621558024.014298",
                "v": 61.96841141134968
            }
        ],
        [
            {
                "n": "Patient_Weight",
                "u": "Kg",
                "t": "1621558027.0254457",
                "v": 62.12459372088554
            }
        ],
        [
            {
                "n": "Patient_Weight",
                "u": "Kg",
                "t": "1621558030.0292268",
                "v": 61.92244249370634
            }
        ],
        [
            {
                "n": "Patient_Weight",
                "u": "Kg",
                "t": "1621558033.03553",
                "v": 62.03909891288199
            }
        ],
        [
            {
                "n": "Patient_Weight",
                "u": "Kg",
                "t": "1621558036.0391946",
                "v": 61.65670279679067
            }
        ],
        [
            {
                "n": "Patient_Weight",
                "u": "Kg",
                "t": "1621558039.0521617",
                "v": 61.736275384942985
            }
        ],
        [
            {
                "n": "Patient_Weight",
                "u": "Kg",
                "t": "1621558042.0702217",
                "v": 61.73020474646359
            }
        ],
        [
            {
                "n": "Patient_Weight",
                "u": "Kg",
                "t": "1621558045.0851858",
                "v": 61.885618086395894
            }
        ],
        [
            {
                "n": "Patient_Weight",
                "u": "Kg",
                "t": "1621558048.0955722",
                "v": 61.834051774782
            }
        ],
        [
            {
                "n": "Patient_Weight",
                "u": "Kg",
                "t": "1621558051.1067154",
                "v": 61.91364059028645
            }
        ],
        [
            {
                "n": "Patient_Weight",
                "u": "Kg",
                "t": "1621558054.1264377",
                "v": 61.78421902585805
            }
        ],
        [
            {
                "n": "Patient_Weight",
                "u": "Kg",
                "t": "1621558057.1461635",
                "v": 61.810508730149834
            }
        ],
        [
            {
                "n": "Patient_Weight",
                "u": "Kg",
                "t": "1621558060.1623516",
                "v": 61.78315289921411
            }
        ],
        [
            {
                "n": "Patient_Weight",
                "u": "Kg",
                "t": "1621558063.1731248",
                "v": 61.687704788062184
            }
        ],
        [
            {
                "n": "Patient_Weight",
                "u": "Kg",
                "t": "1621558066.1880288",
                "v": 61.03329322125026
            }
        ],
        [
            {
                "n": "Patient_Weight",
                "u": "Kg",
                "t": "1621558069.199007",
                "v": 60.88156948927293
            }
        ],
        [
            {
                "n": "Patient_Weight",
                "u": "Kg",
                "t": "1621558072.21447",
                "v": 60.918431510617275
            }
        ],
        [
            {
                "n": "Patient_Weight",
                "u": "Kg",
                "t": "1621558075.2208333",
                "v": 60.939054832254676
            }
        ],
        [
            {
                "n": "Patient_Weight",
                "u": "Kg",
                "t": "1621558078.2312407",
                "v": 60.96309499222749
            }
        ],
        [
            {
                "n": "Patient_Weight",
                "u": "Kg",
                "t": "1621558081.24263",
                "v": 61.182721000349105
            }
        ],
        [
            {
                "n": "Patient_Weight",
                "u": "Kg",
                "t": "1621558084.2510254",
                "v": 61.26779462303578
            }
        ],
        [
            {
                "n": "Patient_Weight",
                "u": "Kg",
                "t": "1621558087.2638276",
                "v": 61.13454651753026
            }
        ],
        [
            {
                "n": "Patient_Weight",
                "u": "Kg",
                "t": "1621558090.271331",
                "v": 60.97703663341593
            }
        ],
        [
            {
                "n": "Patient_Weight",
                "u": "Kg",
                "t": "1621558093.276013",
                "v": 61.139207035580064
            }
        ],
        [
            {
                "n": "Patient_Weight",
                "u": "Kg",
                "t": "1621558096.2889016",
                "v": 61.40108069600033
            }
        ],
        [
            {
                "n": "Patient_Weight",
                "u": "Kg",
                "t": "1621558099.302483",
                "v": 61.47244643829701
            }
        ],
        [
            {
                "n": "Patient_Weight",
                "u": "Kg",
                "t": "1621558102.3188677",
                "v": 61.31174419581398
            }
        ],
        [
            {
                "n": "Patient_Weight",
                "u": "Kg",
                "t": "1621558105.3319414",
                "v": 61.291832135066755
            }
        ],
        [
            {
                "n": "Patient_Weight",
                "u": "Kg",
                "t": "1621558108.3436759",
                "v": 61.05404768206552
            }
        ],
        [
            {
                "n": "Patient_Weight",
                "u": "Kg",
                "t": "1621558111.3543584",
                "v": 61.134396235118786
            }
        ],
        [
            {
                "n": "Patient_Weight",
                "u": "Kg",
                "t": "1621558114.3698957",
                "v": 61.06917352852815
            }
        ],
        [
            {
                "n": "Patient_Weight",
                "u": "Kg",
                "t": "1621558117.3826013",
                "v": 61.20274960381795
            }
        ],
        [
            {
                "n": "Patient_Weight",
                "u": "Kg",
                "t": "1621558120.3865998",
                "v": 61.1274630928861
            }
        ],
        [
            {
                "n": "Patient_Weight",
                "u": "Kg",
                "t": "1621558123.4050481",
                "v": 61.18217995290373
            }
        ],
        [
            {
                "n": "Patient_Weight",
                "u": "Kg",
                "t": "1621558126.4187908",
                "v": 61.094502484498626
            }
        ],
        [
            {
                "n": "Patient_Weight",
                "u": "Kg",
                "t": "1621558129.433208",
                "v": 61.09948656063586
            }
        ],
        [
            {
                "n": "Patient_Weight",
                "u": "Kg",
                "t": "1621558132.446029",
                "v": 61.03677972858461
            }
        ],
        [
            {
                "n": "Patient_Weight",
                "u": "Kg",
                "t": "1621558135.4597535",
                "v": 61.12192515103784
            }
        ]
    ]
}